pyfuncts/__init__.py
pyfuncts/thecolours.py
pyfuncts-0.1.1.dist-info/METADATA
pyfuncts-0.1.1.dist-info/WHEEL
pyfuncts-0.1.1.dist-info/top_level.txt
pyfuncts-0.1.1.dist-info/RECORD
